[{"maxHeight":260,"leftList":[{"level":1,"href":"#voucher-title-0","title":"For BOBCAT","page":1,"height":6},{"level":2,"href":"#voucher-title-0-0","title":"Cab, Body & A/C","page":1,"height":6},{"level":3,"href":"#voucher-title-0-0-0","title":"Air Conditioning Compressor","page":1,"height":6},{"level":3,"href":"#voucher-title-0-0-0","title":"Gas Spring","page":2,"height":6},{"level":3,"href":"#voucher-title-0-0-0","title":"Lift Arm & Tach Kit","page":3,"height":6},{"level":2,"href":"#voucher-title-0-0","title":"Electrical Parts","page":5,"height":6},{"level":3,"href":"#voucher-title-0-0-1","title":"Harness","page":5,"height":6},{"level":3,"href":"#voucher-title-0-0-1","title":"Lamps","page":6,"height":6},{"level":3,"href":"#voucher-title-0-0-1","title":"Sensors","page":8,"height":6},{"level":3,"href":"#voucher-title-0-0-1","title":"Solenoid valve","page":10,"height":6},{"level":3,"href":"#voucher-title-0-0-1","title":"Switch","page":12,"height":6},{"level":2,"href":"#voucher-title-0-0","title":"Engine Spare Parts","page":13,"height":6},{"level":3,"href":"#voucher-title-0-0-2","title":"Belts","page":13,"height":6},{"level":3,"href":"#voucher-title-0-0-2","title":"Crankshaft","page":15,"height":6},{"level":3,"href":"#voucher-title-0-0-2","title":"Cushion Damper","page":16,"height":6},{"level":3,"href":"#voucher-title-0-0-2","title":"Cylinder Head","page":17,"height":6},{"level":3,"href":"#voucher-title-0-0-2","title":"Cylinder Head Gasket","page":19,"height":6},{"level":3,"href":"#voucher-title-0-0-2","title":"Fuel Pump","page":21,"height":6},{"level":3,"href":"#voucher-title-0-0-2","title":"Glow Plug","page":23,"height":6},{"level":3,"href":"#voucher-title-0-0-2","title":"Injectors & Nozzle","page":24,"height":6},{"level":3,"href":"#voucher-title-0-0-2","title":"Muffler","page":26,"height":6},{"level":3,"href":"#voucher-title-0-0-2","title":"Other engine parts","page":27,"height":6},{"level":3,"href":"#voucher-title-0-0-2","title":"Overhaul Gasket","page":29,"height":6},{"level":3,"href":"#voucher-title-0-0-2","title":"Overhaul Kits","page":31,"height":6},{"level":3,"href":"#voucher-title-0-0-2","title":"Radiator, Oil & Fuel Caps","page":34,"height":6},{"level":3,"href":"#voucher-title-0-0-2","title":"Starter Motor","page":35,"height":6},{"level":3,"href":"#voucher-title-0-0-2","title":"Stop Solenoid","page":36,"height":6},{"level":3,"href":"#voucher-title-0-0-2","title":"Thermostat","page":38,"height":6},{"level":3,"href":"#voucher-title-0-0-2","title":"Tube and Pipe","page":39,"height":6},{"level":3,"href":"#voucher-title-0-0-2","title":"Turbocharger","page":40,"height":6},{"level":3,"href":"#voucher-title-0-0-2","title":"Water Pump","page":41,"height":6},{"level":2,"href":"#voucher-title-0-0","title":"Hydraulic Parts","page":43,"height":6},{"level":3,"href":"#voucher-title-0-0-3","title":"Hydraulic Coupler","page":43,"height":6},{"level":2,"href":"#voucher-title-0-0","title":"Maintenance Accessories","page":44,"height":6},{"level":3,"href":"#voucher-title-0-0-4","title":"Air Filter","page":44,"height":6},{"level":3,"href":"#voucher-title-0-0-4","title":"Filter Kit","page":46,"height":6},{"level":3,"href":"#voucher-title-0-0-4","title":"Fuel Filter","page":47,"height":6},{"level":3,"href":"#voucher-title-0-0-4","title":"Hydraulic Filter","page":49,"height":6},{"level":3,"href":"#voucher-title-0-0-4","title":"Oil Filter","page":49,"height":6},{"level":2,"href":"#voucher-title-0-0","title":"Seal Kits","page":50,"height":6},{"level":3,"href":"#voucher-title-0-0-5","title":"Other Seals Kits","page":50,"height":6},{"level":1,"href":"#voucher-title-1","title":"For CASE","page":53,"height":6},{"level":2,"href":"#voucher-title-1-1","title":"Cab, Body & A/C","page":53,"height":6}],"leftHeight":258,"leftFull":true,"middleList":[{"level":3,"href":"#voucher-title-1-1-0","title":"Air Conditioning Compressor","page":53,"height":6},{"level":2,"href":"#voucher-title-1-1","title":"Electrical Parts","page":54,"height":6},{"level":3,"href":"#voucher-title-1-1-1","title":"Ignition Switch","page":54,"height":6},{"level":3,"href":"#voucher-title-1-1-1","title":"Sensors","page":55,"height":6},{"level":3,"href":"#voucher-title-1-1-1","title":"Solenoid valve","page":56,"height":6},{"level":3,"href":"#voucher-title-1-1-1","title":"Solenoid Valve Coil","page":58,"height":6},{"level":2,"href":"#voucher-title-1-1","title":"Engine Spare Parts","page":59,"height":6},{"level":3,"href":"#voucher-title-1-1-2","title":"Fan & Radiator","page":59,"height":6},{"level":3,"href":"#voucher-title-1-1-2","title":"Fuel Pump","page":60,"height":6},{"level":3,"href":"#voucher-title-1-1-2","title":"Injectors & Nozzle","page":62,"height":6},{"level":3,"href":"#voucher-title-1-1-2","title":"Other engine parts","page":65,"height":6},{"level":3,"href":"#voucher-title-1-1-2","title":"Stop Solenoid","page":66,"height":6},{"level":3,"href":"#voucher-title-1-1-2","title":"Turbocharger","page":68,"height":6},{"level":3,"href":"#voucher-title-1-1-2","title":"Water Pump","page":70,"height":6},{"level":2,"href":"#voucher-title-1-1","title":"Hydraulic Parts","page":72,"height":6},{"level":3,"href":"#voucher-title-1-1-3","title":"Hydraulic Pump","page":72,"height":6},{"level":2,"href":"#voucher-title-1-1","title":"Maintenance Accessories","page":73,"height":6},{"level":3,"href":"#voucher-title-1-1-4","title":"Air Filter","page":73,"height":6},{"level":3,"href":"#voucher-title-1-1-4","title":"Fuel Filter","page":74,"height":6},{"level":2,"href":"#voucher-title-1-1","title":"Undercarriage","page":75,"height":6},{"level":3,"href":"#voucher-title-1-1-5","title":"Brake Master Cylinder","page":75,"height":6},{"level":1,"href":"#voucher-title-2","title":"For CAT","page":77,"height":6},{"level":2,"href":"#voucher-title-2-2","title":"Cab, Body & A/C","page":77,"height":6},{"level":3,"href":"#voucher-title-2-2-0","title":"Air Conditioning Compressor","page":77,"height":6},{"level":3,"href":"#voucher-title-2-2-0","title":"Joystick controller","page":79,"height":6},{"level":2,"href":"#voucher-title-2-2","title":"Electrical Parts","page":80,"height":6},{"level":3,"href":"#voucher-title-2-2-1","title":"Controllers & Monitors","page":80,"height":6},{"level":3,"href":"#voucher-title-2-2-1","title":"Ignition Switch","page":81,"height":6},{"level":3,"href":"#voucher-title-2-2-1","title":"Lamps","page":83,"height":6},{"level":3,"href":"#voucher-title-2-2-1","title":"Sensors","page":84,"height":6},{"level":3,"href":"#voucher-title-2-2-1","title":"Solenoid valve","page":87,"height":6},{"level":3,"href":"#voucher-title-2-2-1","title":"Throttle motor ","page":90,"height":6},{"level":2,"href":"#voucher-title-2-2","title":"Engine Spare Parts","page":92,"height":6},{"level":3,"href":"#voucher-title-2-2-2","title":"Alternator","page":92,"height":6},{"level":3,"href":"#voucher-title-2-2-2","title":"Cylinder Head","page":94,"height":6},{"level":3,"href":"#voucher-title-2-2-2","title":"Fan & Radiator","page":95,"height":6},{"level":3,"href":"#voucher-title-2-2-2","title":"Fuel Pump","page":98,"height":6},{"level":3,"href":"#voucher-title-2-2-2","title":"Injection Pump","page":101,"height":6},{"level":3,"href":"#voucher-title-2-2-2","title":"Injectors & Nozzle","page":103,"height":6},{"level":3,"href":"#voucher-title-2-2-2","title":"Muffler","page":106,"height":6},{"level":3,"href":"#voucher-title-2-2-2","title":"Other engine parts","page":108,"height":6},{"level":3,"href":"#voucher-title-2-2-2","title":"Overhaul Gasket","page":110,"height":6},{"level":3,"href":"#voucher-title-2-2-2","title":"Overhaul Kits","page":111,"height":6}],"middleFull":true,"middleHeight":258,"rightList":[{"level":3,"href":"#voucher-title-2-2-2","title":"Radiator, Oil & Fuel Caps","page":113,"height":6},{"level":3,"href":"#voucher-title-2-2-2","title":"Starter Motor","page":115,"height":6},{"level":3,"href":"#voucher-title-2-2-2","title":"Stop Solenoid","page":117,"height":6},{"level":3,"href":"#voucher-title-2-2-2","title":"Thermostat","page":118,"height":6},{"level":3,"href":"#voucher-title-2-2-2","title":"Turbocharger","page":119,"height":6},{"level":3,"href":"#voucher-title-2-2-2","title":"Water Pump","page":122,"height":6},{"level":2,"href":"#voucher-title-2-2","title":"Hydraulic Parts","page":125,"height":6},{"level":3,"href":"#voucher-title-2-2-3","title":"Coupling","page":125,"height":6},{"level":2,"href":"#voucher-title-2-2","title":"Maintenance Accessories","page":126,"height":6},{"level":3,"href":"#voucher-title-2-2-4","title":"Air Filter","page":126,"height":6},{"level":3,"href":"#voucher-title-2-2-4","title":"Filter Kit","page":128,"height":6},{"level":3,"href":"#voucher-title-2-2-4","title":"Fuel Filter","page":130,"height":6},{"level":3,"href":"#voucher-title-2-2-4","title":"Oil Filter","page":132,"height":6},{"level":2,"href":"#voucher-title-2-2","title":"Tools and Accessories","page":134,"height":6},{"level":3,"href":"#voucher-title-2-2-5","title":"Tools","page":134,"height":6},{"level":1,"href":"#voucher-title-3","title":"For CUMMINS","page":136,"height":6},{"level":2,"href":"#voucher-title-3-3","title":"Electrical Parts","page":136,"height":6},{"level":3,"href":"#voucher-title-3-3-0","title":"Solenoid valve","page":136,"height":6},{"level":2,"href":"#voucher-title-3-3","title":"Engine Spare Parts","page":136,"height":6},{"level":3,"href":"#voucher-title-3-3-1","title":"Turbocharger","page":136,"height":6},{"level":1,"href":"#voucher-title-4","title":"For DAEWOO","page":139,"height":6},{"level":2,"href":"#voucher-title-4-4","title":"Engine Spare Parts","page":139,"height":6},{"level":3,"href":"#voucher-title-4-4-0","title":"Water Pump","page":139,"height":6},{"level":1,"href":"#voucher-title-5","title":"For Danfoss","page":141,"height":6},{"level":2,"href":"#voucher-title-5-5","title":"Hydraulic Parts","page":141,"height":6},{"level":3,"href":"#voucher-title-5-5-0","title":"Hydraulic Motor","page":141,"height":6},{"level":1,"href":"#voucher-title-6","title":"For Dodge","page":143,"height":6},{"level":2,"href":"#voucher-title-6-6","title":"Engine Spare Parts","page":143,"height":6},{"level":3,"href":"#voucher-title-6-6-0","title":"Other engine parts","page":143,"height":6},{"level":1,"href":"#voucher-title-7","title":"For Donaldson","page":144,"height":6},{"level":2,"href":"#voucher-title-7-7","title":"Maintenance Accessories","page":144,"height":6},{"level":3,"href":"#voucher-title-7-7-0","title":"Air Filter","page":144,"height":6},{"level":1,"href":"#voucher-title-8","title":"For DOOSAN","page":145,"height":6},{"level":2,"href":"#voucher-title-8-8","title":"Engine Spare Parts","page":145,"height":6},{"level":3,"href":"#voucher-title-8-8-0","title":"Injectors & Nozzle","page":145,"height":6},{"level":3,"href":"#voucher-title-8-8-0","title":"Overhaul Gasket","page":146,"height":6},{"level":3,"href":"#voucher-title-8-8-0","title":"Water Pump","page":148,"height":6},{"level":1,"href":"#voucher-title-9","title":"For Eaton","page":150,"height":6},{"level":2,"href":"#voucher-title-9-9","title":"Hydraulic Parts","page":150,"height":6},{"level":3,"href":"#voucher-title-9-9-0","title":"Hydraulic Motor","page":150,"height":6},{"level":2,"href":"#voucher-title-9-9","title":"Seal Kits","page":151,"height":6},{"level":3,"href":"#voucher-title-9-9-1","title":"Other Seals Kits","page":151,"height":6},{"level":1,"href":"#voucher-title-10","title":"For Ford","page":153,"height":6}],"rightFull":true,"rightHeight":258},null,{"maxHeight":260,"leftList":[{"level":2,"href":"#voucher-title-10-10","title":"Engine Spare Parts","page":153,"height":6},{"level":3,"href":"#voucher-title-10-10-0","title":"Fuel Pump","page":153,"height":6},{"level":3,"href":"#voucher-title-10-10-0","title":"Injectors & Nozzle","page":153,"height":6},{"level":1,"href":"#voucher-title-11","title":"For Genie","page":156,"height":6},{"level":2,"href":"#voucher-title-11-11","title":"Cab, Body & A/C","page":156,"height":6},{"level":3,"href":"#voucher-title-11-11-0","title":"Decal","page":156,"height":6},{"level":3,"href":"#voucher-title-11-11-0","title":"Joystick controller","page":156,"height":6},{"level":2,"href":"#voucher-title-11-11","title":"Electrical Parts","page":158,"height":6},{"level":3,"href":"#voucher-title-11-11-1","title":"Circuit Board","page":158,"height":6},{"level":3,"href":"#voucher-title-11-11-1","title":"Control Box","page":159,"height":6},{"level":3,"href":"#voucher-title-11-11-1","title":"Controllers & Monitors","page":160,"height":6},{"level":3,"href":"#voucher-title-11-11-1","title":"Relay, Contactor & Fuse","page":161,"height":6},{"level":3,"href":"#voucher-title-11-11-1","title":"Solenoid valve","page":163,"height":6},{"level":1,"href":"#voucher-title-12","title":"For HITACHI","page":166,"height":6},{"level":2,"href":"#voucher-title-12-12","title":"Electrical Parts","page":166,"height":6},{"level":3,"href":"#voucher-title-12-12-0","title":"Controllers & Monitors","page":166,"height":6},{"level":3,"href":"#voucher-title-12-12-0","title":"Relay, Contactor & Fuse","page":166,"height":6},{"level":3,"href":"#voucher-title-12-12-0","title":"Sensors","page":168,"height":6},{"level":2,"href":"#voucher-title-12-12","title":"Engine Spare Parts","page":170,"height":6},{"level":3,"href":"#voucher-title-12-12-1","title":"Alternator","page":170,"height":6},{"level":3,"href":"#voucher-title-12-12-1","title":"Connecting Rod","page":172,"height":6},{"level":3,"href":"#voucher-title-12-12-1","title":"Cylinder Head","page":173,"height":6},{"level":3,"href":"#voucher-title-12-12-1","title":"Fan & Radiator","page":176,"height":6},{"level":3,"href":"#voucher-title-12-12-1","title":"Fuel Pump","page":177,"height":6},{"level":3,"href":"#voucher-title-12-12-1","title":"Injectors & Nozzle","page":179,"height":6},{"level":3,"href":"#voucher-title-12-12-1","title":"Muffler","page":182,"height":6},{"level":3,"href":"#voucher-title-12-12-1","title":"Overhaul Gasket","page":184,"height":6},{"level":3,"href":"#voucher-title-12-12-1","title":"Overhaul Kits","page":186,"height":6},{"level":3,"href":"#voucher-title-12-12-1","title":"Radiator, Oil & Fuel Caps","page":187,"height":6},{"level":3,"href":"#voucher-title-12-12-1","title":"Starter Motor","page":188,"height":6},{"level":3,"href":"#voucher-title-12-12-1","title":"Thermostat","page":189,"height":6},{"level":3,"href":"#voucher-title-12-12-1","title":"Turbocharger","page":191,"height":6},{"level":3,"href":"#voucher-title-12-12-1","title":"Water Pump","page":193,"height":6},{"level":2,"href":"#voucher-title-12-12","title":"Hydraulic Parts","page":196,"height":6},{"level":3,"href":"#voucher-title-12-12-2","title":"Coupling","page":196,"height":6},{"level":2,"href":"#voucher-title-12-12","title":"Maintenance Accessories","page":197,"height":6},{"level":3,"href":"#voucher-title-12-12-3","title":"Filter Kit","page":197,"height":6},{"level":3,"href":"#voucher-title-12-12-3","title":"Hydraulic Filter","page":198,"height":6},{"level":2,"href":"#voucher-title-12-12","title":"Seal Kits","page":199,"height":6},{"level":3,"href":"#voucher-title-12-12-4","title":"Arm Cylinder Seal Kit","page":199,"height":6},{"level":3,"href":"#voucher-title-12-12-4","title":"Boom Cylinder Seal Kit ","page":200,"height":6},{"level":3,"href":"#voucher-title-12-12-4","title":"Bucket Cylinder Seal Kit","page":201,"height":6},{"level":1,"href":"#voucher-title-13","title":"For Honda","page":203,"height":6}],"leftHeight":258,"leftFull":true,"middleList":[{"level":2,"href":"#voucher-title-13-13","title":"Electrical Parts","page":203,"height":6},{"level":3,"href":"#voucher-title-13-13-0","title":"Regulator","page":203,"height":6},{"level":2,"href":"#voucher-title-13-13","title":"Engine Spare Parts","page":203,"height":6},{"level":3,"href":"#voucher-title-13-13-1","title":"Fuel Pump","page":203,"height":6},{"level":1,"href":"#voucher-title-14","title":"For HYUNDAI","page":205,"height":6},{"level":2,"href":"#voucher-title-14-14","title":"Electrical Parts","page":205,"height":6},{"level":3,"href":"#voucher-title-14-14-0","title":"Sensors","page":205,"height":6},{"level":3,"href":"#voucher-title-14-14-0","title":"Solenoid valve","page":206,"height":6},{"level":2,"href":"#voucher-title-14-14","title":"Engine Spare Parts","page":208,"height":6},{"level":3,"href":"#voucher-title-14-14-1","title":"Fuel Pump","page":208,"height":6},{"level":3,"href":"#voucher-title-14-14-1","title":"Injectors & Nozzle","page":209,"height":6},{"level":3,"href":"#voucher-title-14-14-1","title":"Other engine parts","page":212,"height":6},{"level":1,"href":"#voucher-title-15","title":"For Ingersoll Rand","page":214,"height":6},{"level":2,"href":"#voucher-title-15-15","title":"Electrical Parts","page":214,"height":6},{"level":3,"href":"#voucher-title-15-15-0","title":"Sensors","page":214,"height":6},{"level":1,"href":"#voucher-title-16","title":"For ISUZU","page":215,"height":6},{"level":2,"href":"#voucher-title-16-16","title":"Electrical Parts","page":215,"height":6},{"level":3,"href":"#voucher-title-16-16-0","title":"Sensors","page":215,"height":6},{"level":2,"href":"#voucher-title-16-16","title":"Engine Spare Parts","page":216,"height":6},{"level":3,"href":"#voucher-title-16-16-1","title":"Injectors & Nozzle","page":216,"height":6},{"level":1,"href":"#voucher-title-17","title":"For JCB","page":219,"height":6},{"level":2,"href":"#voucher-title-17-17","title":"Cab, Body & A/C","page":219,"height":6},{"level":3,"href":"#voucher-title-17-17-0","title":"Joystick controller","page":219,"height":6},{"level":2,"href":"#voucher-title-17-17","title":"Electrical Parts","page":219,"height":6},{"level":3,"href":"#voucher-title-17-17-1","title":"Lamps","page":219,"height":6},{"level":3,"href":"#voucher-title-17-17-1","title":"Sensors","page":220,"height":6},{"level":3,"href":"#voucher-title-17-17-1","title":"Solenoid valve","page":221,"height":6},{"level":2,"href":"#voucher-title-17-17","title":"Engine Spare Parts","page":223,"height":6},{"level":3,"href":"#voucher-title-17-17-2","title":"Fuel Pump","page":223,"height":6},{"level":3,"href":"#voucher-title-17-17-2","title":"Injectors & Nozzle","page":224,"height":6},{"level":3,"href":"#voucher-title-17-17-2","title":"Water Pump","page":226,"height":6},{"level":2,"href":"#voucher-title-17-17","title":"Maintenance Accessories","page":228,"height":6},{"level":3,"href":"#voucher-title-17-17-3","title":"Fuel Filter","page":228,"height":6},{"level":1,"href":"#voucher-title-18","title":"For JLG","page":230,"height":6},{"level":2,"href":"#voucher-title-18-18","title":"Cab, Body & A/C","page":230,"height":6},{"level":3,"href":"#voucher-title-18-18-0","title":"Joystick controller","page":230,"height":6},{"level":2,"href":"#voucher-title-18-18","title":"Electrical Parts","page":231,"height":6},{"level":3,"href":"#voucher-title-18-18-1","title":"Solenoid valve","page":231,"height":6},{"level":1,"href":"#voucher-title-19","title":"For JOHN DEERE","page":234,"height":6},{"level":2,"href":"#voucher-title-19-19","title":"Cab, Body & A/C","page":234,"height":6},{"level":3,"href":"#voucher-title-19-19-0","title":"Air Conditioning Compressor","page":234,"height":6},{"level":3,"href":"#voucher-title-19-19-0","title":"Keys","page":236,"height":6},{"level":3,"href":"#voucher-title-19-19-0","title":"Other Cab Parts","page":237,"height":6}],"middleFull":true,"middleHeight":258,"rightList":[{"level":2,"href":"#voucher-title-19-19","title":"Electrical Parts","page":239,"height":6},{"level":3,"href":"#voucher-title-19-19-1","title":"Cable","page":239,"height":6},{"level":3,"href":"#voucher-title-19-19-1","title":"Controllers & Monitors","page":241,"height":6},{"level":3,"href":"#voucher-title-19-19-1","title":"Ignition Switch","page":241,"height":6},{"level":3,"href":"#voucher-title-19-19-1","title":"Lamps","page":244,"height":6},{"level":3,"href":"#voucher-title-19-19-1","title":"Relay, Contactor & Fuse","page":246,"height":6},{"level":3,"href":"#voucher-title-19-19-1","title":"Sensors","page":248,"height":6},{"level":3,"href":"#voucher-title-19-19-1","title":"Solenoid valve","page":251,"height":6},{"level":3,"href":"#voucher-title-19-19-1","title":"Solenoid Valve Coil","page":253,"height":6},{"level":3,"href":"#voucher-title-19-19-1","title":"Switch","page":255,"height":6},{"level":2,"href":"#voucher-title-19-19","title":"Engine Spare Parts","page":256,"height":6},{"level":3,"href":"#voucher-title-19-19-2","title":"Alternator","page":256,"height":6},{"level":3,"href":"#voucher-title-19-19-2","title":"Belts","page":259,"height":6},{"level":3,"href":"#voucher-title-19-19-2","title":"Fan & Radiator","page":261,"height":6},{"level":3,"href":"#voucher-title-19-19-2","title":"Fuel Pump","page":262,"height":6},{"level":3,"href":"#voucher-title-19-19-2","title":"Injection Pump","page":264,"height":6},{"level":3,"href":"#voucher-title-19-19-2","title":"Injectors & Nozzle","page":266,"height":6},{"level":3,"href":"#voucher-title-19-19-2","title":"Muffler","page":269,"height":6},{"level":3,"href":"#voucher-title-19-19-2","title":"Other engine parts","page":270,"height":6},{"level":3,"href":"#voucher-title-19-19-2","title":"Overhaul Gasket","page":272,"height":6},{"level":3,"href":"#voucher-title-19-19-2","title":"Overhaul Kits","page":274,"height":6},{"level":3,"href":"#voucher-title-19-19-2","title":"Radiator, Oil & Fuel Caps","page":275,"height":6},{"level":3,"href":"#voucher-title-19-19-2","title":"Starter Motor","page":277,"height":6},{"level":3,"href":"#voucher-title-19-19-2","title":"Stop Solenoid","page":279,"height":6},{"level":3,"href":"#voucher-title-19-19-2","title":"Thermostat","page":280,"height":6},{"level":3,"href":"#voucher-title-19-19-2","title":"Turbocharger","page":282,"height":6},{"level":3,"href":"#voucher-title-19-19-2","title":"Water Pump","page":285,"height":6},{"level":2,"href":"#voucher-title-19-19","title":"Hydraulic Parts","page":288,"height":6},{"level":3,"href":"#voucher-title-19-19-3","title":"Bushing","page":288,"height":6},{"level":3,"href":"#voucher-title-19-19-3","title":"Coupling","page":290,"height":6},{"level":3,"href":"#voucher-title-19-19-3","title":"Hydraulic Coupler","page":291,"height":6},{"level":3,"href":"#voucher-title-19-19-3","title":"Hydraulic Pump","page":293,"height":6},{"level":2,"href":"#voucher-title-19-19","title":"Maintenance Accessories","page":294,"height":6},{"level":3,"href":"#voucher-title-19-19-4","title":"Air Filter","page":294,"height":6},{"level":3,"href":"#voucher-title-19-19-4","title":"Filter Kit","page":296,"height":6},{"level":3,"href":"#voucher-title-19-19-4","title":"Fuel Filter","page":298,"height":6},{"level":3,"href":"#voucher-title-19-19-4","title":"Hydraulic Filter","page":300,"height":6},{"level":3,"href":"#voucher-title-19-19-4","title":"Oil Filter","page":302,"height":6},{"level":2,"href":"#voucher-title-19-19","title":"Seal Kits","page":303,"height":6},{"level":3,"href":"#voucher-title-19-19-5","title":"Other Seals Kits","page":303,"height":6},{"level":2,"href":"#voucher-title-19-19","title":"Undercarriage","page":305,"height":6},{"level":3,"href":"#voucher-title-19-19-6","title":"Bearing, Gear & Shaft","page":305,"height":6},{"level":3,"href":"#voucher-title-19-19-6","title":"Clutch Parts","page":307,"height":6}],"rightFull":true,"rightHeight":258},null,{"maxHeight":260,"leftList":[{"level":1,"href":"#voucher-title-20","title":"For KOBELCO","page":311,"height":6},{"level":2,"href":"#voucher-title-20-20","title":"Electrical Parts","page":311,"height":6},{"level":3,"href":"#voucher-title-20-20-0","title":"Sensors","page":311,"height":6},{"level":3,"href":"#voucher-title-20-20-0","title":"Solenoid valve","page":312,"height":6},{"level":2,"href":"#voucher-title-20-20","title":"Engine Spare Parts","page":314,"height":6},{"level":3,"href":"#voucher-title-20-20-1","title":"Injectors & Nozzle","page":314,"height":6},{"level":3,"href":"#voucher-title-20-20-1","title":"Muffler","page":315,"height":6},{"level":3,"href":"#voucher-title-20-20-1","title":"Water Pump","page":317,"height":6},{"level":2,"href":"#voucher-title-20-20","title":"Hydraulic Parts","page":318,"height":6},{"level":3,"href":"#voucher-title-20-20-2","title":"Coupling","page":318,"height":6},{"level":1,"href":"#voucher-title-21","title":"For KOMATSU","page":320,"height":6},{"level":2,"href":"#voucher-title-21-21","title":"Cab, Body & A/C","page":320,"height":6},{"level":3,"href":"#voucher-title-21-21-0","title":"Air Conditioning Compressor","page":320,"height":6},{"level":3,"href":"#voucher-title-21-21-0","title":"Blower Motor","page":322,"height":6},{"level":2,"href":"#voucher-title-21-21","title":"Electrical Parts","page":323,"height":6},{"level":3,"href":"#voucher-title-21-21-1","title":"Controllers & Monitors","page":323,"height":6},{"level":3,"href":"#voucher-title-21-21-1","title":"Ignition Switch","page":325,"height":6},{"level":3,"href":"#voucher-title-21-21-1","title":"Relay, Contactor & Fuse","page":326,"height":6},{"level":3,"href":"#voucher-title-21-21-1","title":"Sensors","page":327,"height":6},{"level":3,"href":"#voucher-title-21-21-1","title":"Solenoid valve","page":330,"height":6},{"level":2,"href":"#voucher-title-21-21","title":"Engine Spare Parts","page":332,"height":6},{"level":3,"href":"#voucher-title-21-21-2","title":"Alternator","page":332,"height":6},{"level":3,"href":"#voucher-title-21-21-2","title":"Belts","page":334,"height":6},{"level":3,"href":"#voucher-title-21-21-2","title":"Cushion Damper","page":335,"height":6},{"level":3,"href":"#voucher-title-21-21-2","title":"Cylinder Head","page":336,"height":6},{"level":3,"href":"#voucher-title-21-21-2","title":"Fan & Radiator","page":338,"height":6},{"level":3,"href":"#voucher-title-21-21-2","title":"Fuel Pump","page":340,"height":6},{"level":3,"href":"#voucher-title-21-21-2","title":"Hose","page":342,"height":6},{"level":3,"href":"#voucher-title-21-21-2","title":"Hydraulic Oil Cooler","page":342,"height":6},{"level":3,"href":"#voucher-title-21-21-2","title":"Injectors & Nozzle","page":343,"height":6},{"level":3,"href":"#voucher-title-21-21-2","title":"Muffler","page":347,"height":6},{"level":3,"href":"#voucher-title-21-21-2","title":"Other engine parts","page":350,"height":6},{"level":3,"href":"#voucher-title-21-21-2","title":"Overhaul Gasket","page":351,"height":6},{"level":3,"href":"#voucher-title-21-21-2","title":"Overhaul Kits","page":353,"height":6},{"level":3,"href":"#voucher-title-21-21-2","title":"Radiator, Oil & Fuel Caps","page":355,"height":6},{"level":3,"href":"#voucher-title-21-21-2","title":"Starter Motor","page":357,"height":6},{"level":3,"href":"#voucher-title-21-21-2","title":"Thermostat","page":360,"height":6},{"level":3,"href":"#voucher-title-21-21-2","title":"Turbocharger","page":361,"height":6},{"level":3,"href":"#voucher-title-21-21-2","title":"Water Pump","page":364,"height":6},{"level":2,"href":"#voucher-title-21-21","title":"Hydraulic Parts","page":367,"height":6},{"level":3,"href":"#voucher-title-21-21-3","title":"Bushing","page":368,"height":6},{"level":3,"href":"#voucher-title-21-21-3","title":"Coupling","page":369,"height":6},{"level":3,"href":"#voucher-title-21-21-3","title":"Hydraulic Hose","page":370,"height":6}],"leftHeight":258,"leftFull":true,"middleList":[{"level":3,"href":"#voucher-title-21-21-3","title":"Hydraulic Pump","page":371,"height":6},{"level":3,"href":"#voucher-title-21-21-3","title":"Main & Relief Valve ","page":372,"height":6},{"level":2,"href":"#voucher-title-21-21","title":"Maintenance Accessories","page":373,"height":6},{"level":3,"href":"#voucher-title-21-21-4","title":"Air Filter","page":373,"height":6},{"level":3,"href":"#voucher-title-21-21-4","title":"Fuel Filter","page":376,"height":6},{"level":3,"href":"#voucher-title-21-21-4","title":"Hydraulic Filter","page":378,"height":6},{"level":3,"href":"#voucher-title-21-21-4","title":"Oil Filter","page":379,"height":6},{"level":2,"href":"#voucher-title-21-21","title":"Seal Kits","page":381,"height":6},{"level":3,"href":"#voucher-title-21-21-5","title":"Arm Cylinder Seal Kit","page":381,"height":6},{"level":3,"href":"#voucher-title-21-21-5","title":"Boom Cylinder Seal Kit ","page":382,"height":6},{"level":3,"href":"#voucher-title-21-21-5","title":"Swivel Joint Seal Kit","page":383,"height":6},{"level":2,"href":"#voucher-title-21-21","title":"Swing Machinery and Final Drive","page":384,"height":6},{"level":3,"href":"#voucher-title-21-21-6","title":"Final Drive Spare Parts","page":384,"height":6},{"level":1,"href":"#voucher-title-22","title":"For KUBOTA","page":386,"height":6},{"level":2,"href":"#voucher-title-22-22","title":"Cab, Body & A/C","page":386,"height":6},{"level":3,"href":"#voucher-title-22-22-0","title":"Air Conditioning Compressor","page":386,"height":6},{"level":2,"href":"#voucher-title-22-22","title":"Electrical Parts","page":387,"height":6},{"level":3,"href":"#voucher-title-22-22-1","title":"Ignition Switch","page":387,"height":6},{"level":3,"href":"#voucher-title-22-22-1","title":"Lamps","page":389,"height":6},{"level":3,"href":"#voucher-title-22-22-1","title":"Regulator","page":391,"height":6},{"level":3,"href":"#voucher-title-22-22-1","title":"Relay, Contactor & Fuse","page":392,"height":6},{"level":3,"href":"#voucher-title-22-22-1","title":"Sensors","page":393,"height":6},{"level":3,"href":"#voucher-title-22-22-1","title":"Solenoid valve","page":395,"height":6},{"level":2,"href":"#voucher-title-22-22","title":"Engine Spare Parts","page":397,"height":6},{"level":3,"href":"#voucher-title-22-22-2","title":"Alternator","page":397,"height":6},{"level":3,"href":"#voucher-title-22-22-2","title":"Belts","page":400,"height":6},{"level":3,"href":"#voucher-title-22-22-2","title":"Connecting Rod","page":401,"height":6},{"level":3,"href":"#voucher-title-22-22-2","title":"Crankshaft","page":403,"height":6},{"level":3,"href":"#voucher-title-22-22-2","title":"Cylinder Head","page":405,"height":6},{"level":3,"href":"#voucher-title-22-22-2","title":"Cylinder Head Gasket","page":409,"height":6},{"level":3,"href":"#voucher-title-22-22-2","title":"Fan & Radiator","page":412,"height":6},{"level":3,"href":"#voucher-title-22-22-2","title":"Fuel Pump","page":414,"height":6},{"level":3,"href":"#voucher-title-22-22-2","title":"Glow Plug","page":417,"height":6},{"level":3,"href":"#voucher-title-22-22-2","title":"Injection Pump","page":420,"height":6},{"level":3,"href":"#voucher-title-22-22-2","title":"Injectors & Nozzle","page":422,"height":6},{"level":3,"href":"#voucher-title-22-22-2","title":"Manifold","page":425,"height":6},{"level":3,"href":"#voucher-title-22-22-2","title":"Oil Pump","page":427,"height":6},{"level":3,"href":"#voucher-title-22-22-2","title":"Other engine parts","page":428,"height":6},{"level":3,"href":"#voucher-title-22-22-2","title":"Overhaul Gasket","page":431,"height":6},{"level":3,"href":"#voucher-title-22-22-2","title":"Overhaul Kits","page":434,"height":6},{"level":3,"href":"#voucher-title-22-22-2","title":"Radiator, Oil & Fuel Caps","page":436,"height":6},{"level":3,"href":"#voucher-title-22-22-2","title":"Starter Motor","page":438,"height":6},{"level":3,"href":"#voucher-title-22-22-2","title":"Stop Solenoid","page":441,"height":6}],"middleFull":true,"middleHeight":258,"rightList":[{"level":3,"href":"#voucher-title-22-22-2","title":"Thermostat","page":443,"height":6},{"level":3,"href":"#voucher-title-22-22-2","title":"Tube and Pipe","page":445,"height":6},{"level":3,"href":"#voucher-title-22-22-2","title":"Turbocharger","page":447,"height":6},{"level":3,"href":"#voucher-title-22-22-2","title":"Water Pump","page":450,"height":6},{"level":2,"href":"#voucher-title-22-22","title":"Hydraulic Parts","page":452,"height":6},{"level":3,"href":"#voucher-title-22-22-3","title":"Hydraulic Pump","page":452,"height":6},{"level":2,"href":"#voucher-title-22-22","title":"Maintenance Accessories","page":454,"height":6},{"level":3,"href":"#voucher-title-22-22-4","title":"Air Filter","page":454,"height":6},{"level":3,"href":"#voucher-title-22-22-4","title":"Filter Kit","page":456,"height":6},{"level":3,"href":"#voucher-title-22-22-4","title":"Fuel Filter","page":458,"height":6},{"level":3,"href":"#voucher-title-22-22-4","title":"Oil Filter","page":461,"height":6},{"level":1,"href":"#voucher-title-23","title":"For Massey Ferguson","page":463,"height":6},{"level":2,"href":"#voucher-title-23-23","title":"Engine Spare Parts","page":463,"height":6},{"level":3,"href":"#voucher-title-23-23-0","title":"Fuel Pump","page":463,"height":6},{"level":3,"href":"#voucher-title-23-23-0","title":"Injectors & Nozzle","page":464,"height":6},{"level":3,"href":"#voucher-title-23-23-0","title":"Water Pump","page":466,"height":6},{"level":2,"href":"#voucher-title-23-23","title":"Hydraulic Parts","page":467,"height":6},{"level":3,"href":"#voucher-title-23-23-1","title":"Hydraulic Pump","page":467,"height":6},{"level":1,"href":"#voucher-title-24","title":"For MITSUBISHI","page":469,"height":6},{"level":2,"href":"#voucher-title-24-24","title":"Engine Spare Parts","page":469,"height":6},{"level":3,"href":"#voucher-title-24-24-0","title":"Injectors & Nozzle","page":469,"height":6},{"level":3,"href":"#voucher-title-24-24-0","title":"Overhaul Gasket","page":470,"height":6},{"level":1,"href":"#voucher-title-25","title":"For New Holland ","page":472,"height":6},{"level":2,"href":"#voucher-title-25-25","title":"Cab, Body & A/C","page":472,"height":6},{"level":3,"href":"#voucher-title-25-25-0","title":"Air Conditioning Compressor","page":472,"height":6},{"level":2,"href":"#voucher-title-25-25","title":"Electrical Parts","page":473,"height":6},{"level":3,"href":"#voucher-title-25-25-1","title":"Ignition Switch","page":473,"height":6},{"level":3,"href":"#voucher-title-25-25-1","title":"Relay, Contactor & Fuse","page":474,"height":6},{"level":3,"href":"#voucher-title-25-25-1","title":"Solenoid valve","page":475,"height":6},{"level":2,"href":"#voucher-title-25-25","title":"Engine Spare Parts","page":477,"height":6},{"level":3,"href":"#voucher-title-25-25-2","title":"Cylinder Head","page":477,"height":6},{"level":3,"href":"#voucher-title-25-25-2","title":"Fuel Pump","page":480,"height":6},{"level":3,"href":"#voucher-title-25-25-2","title":"Injection Pump","page":481,"height":6},{"level":3,"href":"#voucher-title-25-25-2","title":"Injectors & Nozzle","page":483,"height":6},{"level":3,"href":"#voucher-title-25-25-2","title":"Overhaul Gasket","page":486,"height":6},{"level":3,"href":"#voucher-title-25-25-2","title":"Water Pump","page":487,"height":6},{"level":2,"href":"#voucher-title-25-25","title":"Hydraulic Parts","page":489,"height":6},{"level":3,"href":"#voucher-title-25-25-3","title":"Hydraulic Pump","page":489,"height":6},{"level":2,"href":"#voucher-title-25-25","title":"Maintenance Accessories","page":490,"height":6},{"level":3,"href":"#voucher-title-25-25-4","title":"Air Filter","page":490,"height":6},{"level":3,"href":"#voucher-title-25-25-4","title":"Filter Kit","page":491,"height":6},{"level":1,"href":"#voucher-title-26","title":"For Nissan","page":493,"height":6},{"level":2,"href":"#voucher-title-26-26","title":"Engine Spare Parts","page":493,"height":6}],"rightFull":true,"rightHeight":258},null,{"maxHeight":260,"leftList":[{"level":3,"href":"#voucher-title-26-26-0","title":"Overhaul Kits","page":493,"height":6},{"level":1,"href":"#voucher-title-27","title":"For Parker","page":495,"height":6},{"level":2,"href":"#voucher-title-27-27","title":"Hydraulic Parts","page":495,"height":6},{"level":3,"href":"#voucher-title-27-27-0","title":"Hydraulic Hose","page":495,"height":6},{"level":3,"href":"#voucher-title-27-27-0","title":"Hydraulic Motor","page":495,"height":6},{"level":1,"href":"#voucher-title-28","title":"For Polaris","page":497,"height":6},{"level":2,"href":"#voucher-title-28-28","title":"Undercarriage","page":497,"height":6},{"level":3,"href":"#voucher-title-28-28-0","title":"Clutch Parts","page":497,"height":6},{"level":1,"href":"#voucher-title-29","title":"For Spal","page":499,"height":6},{"level":2,"href":"#voucher-title-29-29","title":"Engine Spare Parts","page":499,"height":6},{"level":3,"href":"#voucher-title-29-29-0","title":"Fan & Radiator","page":499,"height":6},{"level":1,"href":"#voucher-title-30","title":"For Sun Hydraulics","page":501,"height":6},{"level":2,"href":"#voucher-title-30-30","title":"Hydraulic Parts","page":501,"height":6},{"level":3,"href":"#voucher-title-30-30-0","title":"Main & Relief Valve ","page":501,"height":6},{"level":1,"href":"#voucher-title-31","title":"For Takeuchi","page":503,"height":6},{"level":2,"href":"#voucher-title-31-31","title":"Engine Spare Parts","page":503,"height":6},{"level":3,"href":"#voucher-title-31-31-0","title":"Overhaul Gasket","page":503,"height":6},{"level":1,"href":"#voucher-title-32","title":"For Thermo King","page":505,"height":6},{"level":2,"href":"#voucher-title-32-32","title":"Cab, Body & A/C","page":505,"height":6},{"level":3,"href":"#voucher-title-32-32-0","title":"Air Conditioning Compressor","page":505,"height":6},{"level":2,"href":"#voucher-title-32-32","title":"Engine Spare Parts","page":505,"height":6},{"level":3,"href":"#voucher-title-32-32-1","title":"Belts","page":505,"height":6},{"level":1,"href":"#voucher-title-33","title":"For Toyota","page":508,"height":6},{"level":2,"href":"#voucher-title-33-33","title":"Engine Spare Parts","page":508,"height":6},{"level":3,"href":"#voucher-title-33-33-0","title":"Injectors & Nozzle","page":508,"height":6},{"level":1,"href":"#voucher-title-34","title":"For VOLVO","page":510,"height":6},{"level":2,"href":"#voucher-title-34-34","title":"Cab, Body & A/C","page":510,"height":6},{"level":3,"href":"#voucher-title-34-34-0","title":"Air Conditioning Compressor","page":510,"height":6},{"level":2,"href":"#voucher-title-34-34","title":"Electrical Parts","page":511,"height":6},{"level":3,"href":"#voucher-title-34-34-1","title":"Sensors","page":511,"height":6},{"level":3,"href":"#voucher-title-34-34-1","title":"Solenoid valve","page":513,"height":6},{"level":2,"href":"#voucher-title-34-34","title":"Engine Spare Parts","page":515,"height":6},{"level":3,"href":"#voucher-title-34-34-2","title":"Brake Air Compressor","page":515,"height":6},{"level":3,"href":"#voucher-title-34-34-2","title":"Fan & Radiator","page":516,"height":6},{"level":3,"href":"#voucher-title-34-34-2","title":"Fuel Pump","page":517,"height":6},{"level":3,"href":"#voucher-title-34-34-2","title":"Injectors & Nozzle","page":520,"height":6},{"level":3,"href":"#voucher-title-34-34-2","title":"Other engine parts","page":522,"height":6},{"level":3,"href":"#voucher-title-34-34-2","title":"Turbocharger","page":523,"height":6},{"level":3,"href":"#voucher-title-34-34-2","title":"Water Pump","page":526,"height":6},{"level":2,"href":"#voucher-title-34-34","title":"Maintenance Accessories","page":528,"height":6},{"level":3,"href":"#voucher-title-34-34-3","title":"Air Filter","page":528,"height":6},{"level":3,"href":"#voucher-title-34-34-3","title":"Fuel Filter","page":529,"height":6},{"level":1,"href":"#voucher-title-35","title":"For Woodward","page":532,"height":6}],"leftHeight":258,"leftFull":true,"middleList":[{"level":2,"href":"#voucher-title-35-35","title":"Electrical Parts","page":532,"height":6},{"level":3,"href":"#voucher-title-35-35-0","title":"Solenoid valve","page":532,"height":6},{"level":2,"href":"#voucher-title-35-35","title":"Engine Spare Parts","page":533,"height":6},{"level":3,"href":"#voucher-title-35-35-1","title":"Stop Solenoid","page":533,"height":6},{"level":1,"href":"#voucher-title-36","title":"For Yamaha","page":535,"height":6},{"level":2,"href":"#voucher-title-36-36","title":"Engine Spare Parts","page":535,"height":6},{"level":3,"href":"#voucher-title-36-36-0","title":"Fuel Pump","page":535,"height":6},{"level":1,"href":"#voucher-title-37","title":"For YANMAR","page":536,"height":6},{"level":2,"href":"#voucher-title-37-37","title":"Engine Spare Parts","page":536,"height":6},{"level":3,"href":"#voucher-title-37-37-0","title":"Overhaul Gasket","page":536,"height":6},{"level":3,"href":"#voucher-title-37-37-0","title":"Overhaul Kits","page":537,"height":6},{"level":3,"href":"#voucher-title-37-37-0","title":"Water Pump","page":539,"height":6},{"level":2,"href":"#voucher-title-37-37","title":"Maintenance Accessories","page":540,"height":6},{"level":3,"href":"#voucher-title-37-37-1","title":"Fuel Filter","page":540,"height":6},{"level":1,"href":"#voucher-title-38","title":"For Other Brands","page":542,"height":6},{"level":2,"href":"#voucher-title-38-38","title":"Cab, Body & A/C","page":542,"height":6},{"level":3,"href":"#voucher-title-38-38-0","title":"Air Conditioning Compressor","page":542,"height":6},{"level":3,"href":"#voucher-title-38-38-0","title":"Joystick controller","page":544,"height":6},{"level":3,"href":"#voucher-title-38-38-0","title":"Keys","page":544,"height":6},{"level":3,"href":"#voucher-title-38-38-0","title":"Other Cab Parts","page":545,"height":6},{"level":2,"href":"#voucher-title-38-38","title":"Electrical Parts","page":547,"height":6},{"level":3,"href":"#voucher-title-38-38-1","title":"Battery Charger","page":547,"height":6},{"level":3,"href":"#voucher-title-38-38-1","title":"Cable","page":547,"height":6},{"level":3,"href":"#voucher-title-38-38-1","title":"Controllers & Monitors","page":548,"height":6},{"level":3,"href":"#voucher-title-38-38-1","title":"Gauge, Meter & Indicator","page":550,"height":6},{"level":3,"href":"#voucher-title-38-38-1","title":"Harness","page":551,"height":6},{"level":3,"href":"#voucher-title-38-38-1","title":"Ignition Switch","page":552,"height":6},{"level":3,"href":"#voucher-title-38-38-1","title":"Other Electrical Parts","page":553,"height":6},{"level":3,"href":"#voucher-title-38-38-1","title":"Pressure Switch","page":555,"height":6},{"level":3,"href":"#voucher-title-38-38-1","title":"PTO Switch","page":557,"height":6},{"level":3,"href":"#voucher-title-38-38-1","title":"Regulator","page":558,"height":6},{"level":3,"href":"#voucher-title-38-38-1","title":"Relay, Contactor & Fuse","page":559,"height":6},{"level":3,"href":"#voucher-title-38-38-1","title":"Sensors","page":560,"height":6},{"level":3,"href":"#voucher-title-38-38-1","title":"Solenoid valve","page":562,"height":6},{"level":3,"href":"#voucher-title-38-38-1","title":"Solenoid Valve Coil","page":564,"height":6},{"level":3,"href":"#voucher-title-38-38-1","title":"Speed Governor & Actuator","page":566,"height":6},{"level":3,"href":"#voucher-title-38-38-1","title":"Switch","page":567,"height":6},{"level":2,"href":"#voucher-title-38-38","title":"Engine Spare Parts","page":569,"height":6},{"level":3,"href":"#voucher-title-38-38-2","title":"Alternator","page":569,"height":6},{"level":3,"href":"#voucher-title-38-38-2","title":"Belts","page":570,"height":6},{"level":3,"href":"#voucher-title-38-38-2","title":"Cylinder Head","page":570,"height":6},{"level":3,"href":"#voucher-title-38-38-2","title":"Cylinder Head Gasket","page":574,"height":6},{"level":3,"href":"#voucher-title-38-38-2","title":"Engine Block Heater","page":576,"height":6}],"middleFull":true,"middleHeight":258,"rightList":[{"level":3,"href":"#voucher-title-38-38-2","title":"Fuel Pump","page":576,"height":6},{"level":3,"href":"#voucher-title-38-38-2","title":"Injectors & Nozzle","page":578,"height":6},{"level":3,"href":"#voucher-title-38-38-2","title":"Other engine parts","page":581,"height":6},{"level":3,"href":"#voucher-title-38-38-2","title":"Overhaul Gasket","page":582,"height":6},{"level":3,"href":"#voucher-title-38-38-2","title":"Overhaul Kits","page":584,"height":6},{"level":3,"href":"#voucher-title-38-38-2","title":"Starter Motor","page":587,"height":6},{"level":3,"href":"#voucher-title-38-38-2","title":"Stop Solenoid","page":590,"height":6},{"level":3,"href":"#voucher-title-38-38-2","title":"Turbocharger","page":591,"height":6},{"level":3,"href":"#voucher-title-38-38-2","title":"Water Pump","page":593,"height":6},{"level":2,"href":"#voucher-title-38-38","title":"Hydraulic Parts","page":596,"height":6},{"level":3,"href":"#voucher-title-38-38-3","title":"Coupling","page":596,"height":6},{"level":3,"href":"#voucher-title-38-38-3","title":"Hydraulic Motor","page":596,"height":6},{"level":2,"href":"#voucher-title-38-38","title":"Maintenance Accessories","page":597,"height":6},{"level":3,"href":"#voucher-title-38-38-4","title":"Air Filter","page":597,"height":6},{"level":3,"href":"#voucher-title-38-38-4","title":"Filter Kit","page":598,"height":6},{"level":3,"href":"#voucher-title-38-38-4","title":"Fuel Filter","page":599,"height":6},{"level":2,"href":"#voucher-title-38-38","title":"Tools and Accessories","page":601,"height":6},{"level":3,"href":"#voucher-title-38-38-5","title":"Replace Deutsch Connector","page":601,"height":6},{"level":3,"href":"#voucher-title-38-38-5","title":"Tools","page":602,"height":6},{"level":2,"href":"#voucher-title-38-38","title":"Undercarriage","page":603,"height":6},{"level":3,"href":"#voucher-title-38-38-6","title":"Bearing, Gear & Shaft","page":603,"height":6},{"level":3,"href":"#voucher-title-38-38-6","title":"Brake Discs, Pads & Calipers","page":604,"height":6},{"level":3,"href":"#voucher-title-38-38-6","title":"Clutch Parts","page":605,"height":6},{"level":3,"href":"#voucher-title-38-38-6","title":"Other Transmission Parts","page":606,"height":6}],"rightFull":false,"rightHeight":144}]